{
  "symbol": "PEKAO",
  "companyName": "Bank Pekao SA",
  "quoteUrl": "https://www.bankier.pl/inwestowanie/profile/quote.html?symbol=PEKAO",
  "forumUrl": "https://www.bankier.pl/forum/forum_o_bank-polska-kasa-opieki-sa,6,21,18.html",
  "updatedAt": "2026-03-12T11:24:04.893Z",
  "report": {
    "available": true,
    "source": "Bankier.pl forum",
    "fetchedAt": "2026-03-12T11:24:04.893Z",
    "commentLimit": 5
  },
  "analysis": {
    "signal": "HOLD",
    "score": 0,
    "confidence": 0.75,
    "commentCount": 5,
    "summary": "Ostatnie zebrane komentarze są mieszane; sygnał wynika z pełnej treści wpisów, słów kluczowych i proporcji komentarzy dodatnich do ujemnych.",
    "topKeywords": [
      {
        "word": "oczywiście",
        "count": 1
      },
      {
        "word": "pożyjemy",
        "count": 1
      },
      {
        "word": "zobaczymy",
        "count": 1
      },
      {
        "word": "funde",
        "count": 1
      },
      {
        "word": "lubią",
        "count": 1
      },
      {
        "word": "dywidendę",
        "count": 1
      },
      {
        "word": "chyba",
        "count": 1
      },
      {
        "word": "jednak",
        "count": 1
      }
    ]
  },
  "comments": [
    {
      "id": "73764613",
      "author": "OCZYWIŚCIE",
      "postedAt": "2026-03-09 10:00",
      "threadTitle": "Re: Myślicie, że spadnie na 150?",
      "url": "https://www.bankier.pl/forum/temat_myslicie-ze-spadnie-na-150,73749353.html",
      "body": "OCZYWIŚCIE ŻE TAK !!!!!",
      "sentimentScore": 0,
      "sentimentLabel": "Neutral"
    },
    {
      "id": "73759283",
      "author": "krzywamordamoravera",
      "postedAt": "2026-03-08 20:34",
      "threadTitle": "Re: Myślicie, że spadnie na 150?",
      "url": "https://www.bankier.pl/forum/temat_myslicie-ze-spadnie-na-150,73749353.html",
      "body": "Pożyjemy zobaczymy funde lubią dywidendę",
      "sentimentScore": 0,
      "sentimentLabel": "Neutral"
    },
    {
      "id": "73758705",
      "author": "jim_morris",
      "postedAt": "2026-03-08 19:19",
      "threadTitle": "Re: Myślicie, że spadnie na 150?",
      "url": "https://www.bankier.pl/forum/temat_myslicie-ze-spadnie-na-150,73749353.html",
      "body": "Chyba jednak bardziej 170 przy tej dywidendzie.",
      "sentimentScore": 0,
      "sentimentLabel": "Neutral"
    },
    {
      "id": "73757609",
      "author": "Adam",
      "postedAt": "2026-03-08 16:30",
      "threadTitle": "Re: Myślicie, że spadnie na 150?",
      "url": "https://www.bankier.pl/forum/temat_myslicie-ze-spadnie-na-150,73749353.html",
      "body": "Rok temu w kwietniu też kupowałem po 150 także szansa jest",
      "sentimentScore": 0,
      "sentimentLabel": "Neutral"
    },
    {
      "id": "73747773",
      "author": "Dghh",
      "postedAt": "2026-03-07 06:58",
      "threadTitle": "Re: taka sytuacja - akcje już sprzedałem",
      "url": "https://www.bankier.pl/forum/temat_taka-sytuacja-akcje-juz-sprzeda-em,73429809.html",
      "body": "pewno będzie beneficjentem tego programubęda Niemcy",
      "sentimentScore": 0,
      "sentimentLabel": "Neutral"
    }
  ]
}
